LICENSE.md
MANIFEST.in
README.md
pyproject.toml
setup.py
eqtools/AUGData.py
eqtools/CModEFIT.py
eqtools/D3DEFIT.py
eqtools/EFIT.py
eqtools/FromArrays.py
eqtools/NSTXEFIT.py
eqtools/TCVLIUQE.py
eqtools/__init__.py
eqtools/_tricub.c
eqtools/_tricub.pyf
eqtools/_tricubmodule.c
eqtools/afilereader.py
eqtools/core.py
eqtools/eqdskreader.py
eqtools/filewriter.py
eqtools/pfilereader.py
eqtools/trispline.py
eqtools.egg-info/PKG-INFO
eqtools.egg-info/SOURCES.txt
eqtools.egg-info/dependency_links.txt
eqtools.egg-info/requires.txt
eqtools.egg-info/top_level.txt
tests/test.py
tests/test_scratch.py