Metadata-Version: 2.4
Name: eqtools
Version: 1.5.0
Summary: Python tools for magnetic equilibria in tokamak plasmas
Home-page: https://github.com/PSFCPlasmaTools/eqtools/
Author: Mark Chilenski, Ian Faust, John Walk
Author-email: psfcplasmatools@mit.edu
Project-URL: Homepage, https://github.com/PSFCPlasmaTools/eqtools/
License-File: LICENSE.md
Requires-Dist: numpy
Requires-Dist: scipy
Requires-Dist: matplotlib
Dynamic: author-email
Dynamic: home-page
Dynamic: license-file
